MANIFEST.in
README.md
README.rst
setup.py
django_queued_storage_fork.egg-info/PKG-INFO
django_queued_storage_fork.egg-info/SOURCES.txt
django_queued_storage_fork.egg-info/dependency_links.txt
django_queued_storage_fork.egg-info/not-zip-safe
django_queued_storage_fork.egg-info/requires.txt
django_queued_storage_fork.egg-info/top_level.txt
queued_storage/__init__.py
queued_storage/backend.py
queued_storage/fields.py
queued_storage/models.py
queued_storage/tasks.py
queued_storage/tests/__init__.py
queued_storage/tests/test.png