Metadata-Version: 1.0
Name: django-queued-storage-fork
Version: 0.3
Summary: Allows for files to be uploaded locally and then transferred to a remote location. This is a fork because the original is not online.
Home-page: UNKNOWN
Author: Alen Mujezinovic
Author-email: alen@caffeinehit.com
License: UNKNOWN
Platform: UNKNOWN
Classifier: Programming Language :: Python
Classifier: Environment :: Web Environment
Classifier: Intended Audience :: Developers
Classifier: Operating System :: OS Independent
Classifier: Framework :: Django
